iker/setup/__init__.py
iker_python_setup-1.0.999999.dist-info/METADATA
iker_python_setup-1.0.999999.dist-info/WHEEL
iker_python_setup-1.0.999999.dist-info/top_level.txt
iker_python_setup-1.0.999999.dist-info/RECORD
